gama/GamaClassifier.py
gama/GamaRegressor.py
gama/__init__.py
gama/__version__.py
gama/data_formatting.py
gama/data_loading.py
gama/gama.py
gama/configuration/__init__.py
gama/configuration/classification.py
gama/configuration/parser.py
gama/configuration/regression.py
gama/configuration/testconfiguration.py
gama/genetic_programming/__init__.py
gama/genetic_programming/crossover.py
gama/genetic_programming/mutation.py
gama/genetic_programming/nsga2.py
gama/genetic_programming/operations.py
gama/genetic_programming/operator_set.py
gama/genetic_programming/selection.py
gama/genetic_programming/compilers/__init__.py
gama/genetic_programming/compilers/scikitlearn.py
gama/genetic_programming/components/__init__.py
gama/genetic_programming/components/fitness.py
gama/genetic_programming/components/individual.py
gama/genetic_programming/components/primitive.py
gama/genetic_programming/components/primitive_node.py
gama/genetic_programming/components/terminal.py
gama/logging/GamaReport.py
gama/logging/__init__.py
gama/logging/evaluation_logger.py
gama/logging/utility_functions.py
gama/postprocessing/__init__.py
gama/postprocessing/base_post_processing.py
gama/postprocessing/best_fit.py
gama/postprocessing/ensemble.py
gama/search_methods/__init__.py
gama/search_methods/asha.py
gama/search_methods/async_ea.py
gama/search_methods/base_search.py
gama/search_methods/random_search.py
gama/utilities/__init__.py
gama/utilities/cli.py
gama/utilities/evaluation_library.py
gama/utilities/export.py
gama/utilities/metrics.py
gama/utilities/preprocessing.py
gama/utilities/generic/__init__.py
gama/utilities/generic/async_evaluator.py
gama/utilities/generic/paretofront.py
gama/utilities/generic/stopwatch.py
gama/utilities/generic/timekeeper.py
gama-23.0.0.post1.dist-info/LICENSE
gama-23.0.0.post1.dist-info/METADATA
gama-23.0.0.post1.dist-info/WHEEL
gama-23.0.0.post1.dist-info/entry_points.txt
gama-23.0.0.post1.dist-info/top_level.txt
gama-23.0.0.post1.dist-info/RECORD
