Metadata-Version: 2.1
Name: gama
Version: 23.0.0.post1
Summary: A package for automated machine learning based on scikit-learn.
Author-email: Pieter Gijsbers <p.gijsbers@tue.nl>
License: MIT
Classifier: License :: OSI Approved :: MIT License
Classifier: Programming Language :: Python :: 3
Requires-Python: >=3.9
License-File: LICENSE
Requires-Dist: numpy >=1.20.0
Requires-Dist: scipy >=1.0.0
Requires-Dist: scikit-learn <1.3,>=1.1.0
Requires-Dist: pandas >=1.0
Requires-Dist: stopit >=1.1.1
Requires-Dist: liac-arff >=2.2.2
Requires-Dist: category-encoders >=1.2.8
Requires-Dist: black ==24.3.0
Requires-Dist: psutil
Provides-Extra: doc
Requires-Dist: sphinx ; extra == 'doc'
Requires-Dist: sphinx-rtd-theme ; extra == 'doc'
Provides-Extra: test
Requires-Dist: pre-commit ==3.2.2 ; extra == 'test'
Requires-Dist: pytest >=4.4.0 ; extra == 'test'
Requires-Dist: pytest-mock ; extra == 'test'
Requires-Dist: pytest-xdist ; extra == 'test'
Requires-Dist: codecov ; extra == 'test'
Requires-Dist: pytest-cov ; extra == 'test'
